{
  "fonte_diario": "C:/Users/Ruds/Desktop/ROADMAP MKT OFFICE JUN 2026/03 LinkedIn Boost/Linkedin followers_maio 2025 ate maio 2026.xls",
  "fonte_reports": "C:/Users/Ruds/OneDrive - EPI USE BRASIL SERVIÇOS EM SISTEMAS LTDA/MARKETING/Reports/Relatorio MKT",
  "gerado_em": "2026-06-19T10:24:59.681104",
  "resumo": {
    "periodo_diario": "2025-08-01 a 2026-05-23",
    "total_ganho_periodo": 1456,
    "dias_com_ganho": 264,
    "dias_total": 296,
    "media_diaria": 4.92,
    "total_via_eventos": 227,
    "pct_eventos": 15.6,
    "ultimo_total_reportado": 10640
  },
  "serie_mensal": [
    {
      "mes": "2025-01",
      "total_seguidores": 8202,
      "novos": 111,
      "newsletter": 3306,
      "posts_mes": 50,
      "impressoes": 19567,
      "fonte": "report-pptx",
      "arquivo": "01 - EPI-USE _ Marketing 2025 - Janeiro.pptx"
    },
    {
      "mes": "2025-02",
      "total_seguidores": 8439,
      "novos": 216,
      "newsletter": 3424,
      "posts_mes": 55,
      "impressoes": 27798,
      "fonte": "report-pptx",
      "arquivo": "02 - EPI-USE _ Marketing 2025 - Fevereiro.pptx"
    },
    {
      "mes": "2025-03",
      "total_seguidores": 8634,
      "novos": 219,
      "newsletter": 3511,
      "posts_mes": 40,
      "impressoes": 20104,
      "fonte": "report-pptx",
      "arquivo": "03 - EPI-USE _ Marketing 2025 - Março.pptx"
    },
    {
      "mes": "2025-04",
      "total_seguidores": 8634,
      "novos": 219,
      "newsletter": 3511,
      "posts_mes": null,
      "impressoes": 20104,
      "fonte": "report-pptx",
      "arquivo": "04 - EPI-USE _ Marketing 2025 - Abril.pptx"
    },
    {
      "mes": "2025-05",
      "total_seguidores": 8966,
      "novos": 164,
      "newsletter": 3624,
      "posts_mes": null,
      "impressoes": 21671,
      "fonte": "report-pptx",
      "arquivo": "05 - EPI-USE _ Marketing 2025 - Maio.pptx"
    },
    {
      "mes": "2025-06",
      "total_seguidores": 9062,
      "novos": 101,
      "newsletter": 3700,
      "posts_mes": null,
      "impressoes": null,
      "fonte": "report-pptx",
      "arquivo": "06 - EPI-USE _ Marketing 2025 - Junho.pptx"
    },
    {
      "mes": "2025-07",
      "total_seguidores": 9257,
      "novos": 183,
      "newsletter": 3723,
      "posts_mes": null,
      "impressoes": null,
      "fonte": "report-pptx",
      "arquivo": "07 - EPI-USE _ Marketing 2025 - Julho.pptx"
    },
    {
      "mes": "2025-08",
      "total_seguidores": 9525,
      "novos": 291,
      "newsletter": 3730,
      "posts_mes": null,
      "impressoes": null,
      "fonte": "report-pptx",
      "arquivo": "08 - EPI-USE _ Marketing 2025 - Agosto.pptx",
      "novos_diario": 291,
      "dias_com_ganho": 29
    },
    {
      "mes": "2025-09",
      "total_seguidores": null,
      "novos": 91,
      "newsletter": null,
      "posts_mes": null,
      "impressoes": null,
      "fonte": "xls-diario"
    },
    {
      "mes": "2025-10",
      "total_seguidores": 9769,
      "novos": 148,
      "newsletter": 3704,
      "posts_mes": null,
      "impressoes": null,
      "fonte": "report-pptx",
      "arquivo": "10 - EPI-USE _ Marketing 2025 - Outubro.pptx",
      "novos_diario": 148,
      "dias_com_ganho": 27
    },
    {
      "mes": "2025-11",
      "total_seguidores": 9827,
      "novos": 96,
      "newsletter": 3703,
      "posts_mes": null,
      "impressoes": null,
      "fonte": "report-pptx",
      "arquivo": "11 - EPI-USE _ Marketing 2025 - Novembro.pptx",
      "novos_diario": 86,
      "dias_com_ganho": 27
    },
    {
      "mes": "2025-12",
      "total_seguidores": null,
      "novos": 74,
      "newsletter": null,
      "posts_mes": null,
      "impressoes": null,
      "fonte": "xls-diario"
    },
    {
      "mes": "2026-01",
      "total_seguidores": null,
      "novos": 109,
      "newsletter": null,
      "posts_mes": null,
      "impressoes": null,
      "fonte": "xls-diario"
    },
    {
      "mes": "2026-02",
      "total_seguidores": 10163,
      "novos": 125,
      "newsletter": 3698,
      "posts_mes": null,
      "impressoes": null,
      "fonte": "report-pptx",
      "arquivo": "02 - EPI-USE _ Marketing 2026 - Fevereiro.pptx",
      "novos_diario": 124,
      "dias_com_ganho": 24
    },
    {
      "mes": "2026-03",
      "total_seguidores": 10379,
      "novos": 231,
      "newsletter": 3698,
      "posts_mes": null,
      "impressoes": null,
      "fonte": "report-pptx",
      "arquivo": "03 - EPI-USE _ Marketing 2026 - Março.pptx",
      "novos_diario": 231,
      "dias_com_ganho": 31
    },
    {
      "mes": "2026-04",
      "total_seguidores": 10481,
      "novos": 149,
      "newsletter": 3698,
      "posts_mes": null,
      "impressoes": null,
      "fonte": "report-pptx",
      "arquivo": "04 - EPI-USE _ Marketing 2026 - Abril.pptx",
      "novos_diario": 148,
      "dias_com_ganho": 28
    },
    {
      "mes": "2026-05",
      "total_seguidores": 10640,
      "novos": 178,
      "newsletter": 3698,
      "posts_mes": null,
      "impressoes": null,
      "fonte": "manual (Rudá 2026-05-30) + xls",
      "arquivo": "05 - EPI-USE _ Marketing 2026 - Maio.pptx",
      "novos_diario": 154,
      "dias_com_ganho": 22
    }
  ],
  "serie_diaria": [
    {
      "data": "2025-08-01",
      "patrocinados": 0,
      "organicos": 6,
      "convidados": 0,
      "total": 6,
      "evento": null
    },
    {
      "data": "2025-08-02",
      "patrocinados": 0,
      "organicos": 2,
      "convidados": 0,
      "total": 2,
      "evento": null
    },
    {
      "data": "2025-08-03",
      "patrocinados": 0,
      "organicos": 3,
      "convidados": 0,
      "total": 3,
      "evento": null
    },
    {
      "data": "2025-08-04",
      "patrocinados": 0,
      "organicos": 3,
      "convidados": 0,
      "total": 3,
      "evento": null
    },
    {
      "data": "2025-08-05",
      "patrocinados": 0,
      "organicos": 8,
      "convidados": 0,
      "total": 8,
      "evento": null
    },
    {
      "data": "2025-08-06",
      "patrocinados": 0,
      "organicos": 5,
      "convidados": 0,
      "total": 5,
      "evento": null
    },
    {
      "data": "2025-08-07",
      "patrocinados": 0,
      "organicos": 4,
      "convidados": 0,
      "total": 4,
      "evento": null
    },
    {
      "data": "2025-08-08",
      "patrocinados": 0,
      "organicos": 8,
      "convidados": 0,
      "total": 8,
      "evento": null
    },
    {
      "data": "2025-08-09",
      "patrocinados": 0,
      "organicos": 4,
      "convidados": 0,
      "total": 4,
      "evento": null
    },
    {
      "data": "2025-08-10",
      "patrocinados": 0,
      "organicos": 1,
      "convidados": 0,
      "total": 1,
      "evento": null
    },
    {
      "data": "2025-08-11",
      "patrocinados": 0,
      "organicos": 3,
      "convidados": 0,
      "total": 3,
      "evento": null
    },
    {
      "data": "2025-08-12",
      "patrocinados": 0,
      "organicos": 5,
      "convidados": 0,
      "total": 5,
      "evento": null
    },
    {
      "data": "2025-08-13",
      "patrocinados": 0,
      "organicos": 8,
      "convidados": 0,
      "total": 8,
      "evento": null
    },
    {
      "data": "2025-08-14",
      "patrocinados": 0,
      "organicos": 8,
      "convidados": 0,
      "total": 8,
      "evento": null
    },
    {
      "data": "2025-08-15",
      "patrocinados": 0,
      "organicos": 3,
      "convidados": 0,
      "total": 3,
      "evento": null
    },
    {
      "data": "2025-08-16",
      "patrocinados": 0,
      "organicos": 1,
      "convidados": 0,
      "total": 1,
      "evento": null
    },
    {
      "data": "2025-08-17",
      "patrocinados": 0,
      "organicos": 1,
      "convidados": 0,
      "total": 1,
      "evento": null
    },
    {
      "data": "2025-08-18",
      "patrocinados": 0,
      "organicos": 3,
      "convidados": 0,
      "total": 3,
      "evento": null
    },
    {
      "data": "2025-08-19",
      "patrocinados": 0,
      "organicos": 72,
      "convidados": 0,
      "total": 72,
      "evento": "SAP NOW 2026"
    },
    {
      "data": "2025-08-20",
      "patrocinados": 0,
      "organicos": 101,
      "convidados": 0,
      "total": 101,
      "evento": "SAP NOW 2025"
    },
    {
      "data": "2025-08-21",
      "patrocinados": 0,
      "organicos": 3,
      "convidados": 0,
      "total": 3,
      "evento": null
    },
    {
      "data": "2025-08-22",
      "patrocinados": 0,
      "organicos": 7,
      "convidados": 0,
      "total": 7,
      "evento": null
    },
    {
      "data": "2025-08-23",
      "patrocinados": 0,
      "organicos": 1,
      "convidados": 0,
      "total": 1,
      "evento": null
    },
    {
      "data": "2025-08-24",
      "patrocinados": 0,
      "organicos": 0,
      "convidados": 0,
      "total": 0,
      "evento": null
    },
    {
      "data": "2025-08-25",
      "patrocinados": 0,
      "organicos": 3,
      "convidados": 0,
      "total": 3,
      "evento": null
    },
    {
      "data": "2025-08-26",
      "patrocinados": 0,
      "organicos": 8,
      "convidados": 0,
      "total": 8,
      "evento": null
    },
    {
      "data": "2025-08-27",
      "patrocinados": 0,
      "organicos": 7,
      "convidados": 0,
      "total": 7,
      "evento": null
    },
    {
      "data": "2025-08-28",
      "patrocinados": 0,
      "organicos": 9,
      "convidados": 0,
      "total": 9,
      "evento": null
    },
    {
      "data": "2025-08-29",
      "patrocinados": 0,
      "organicos": 3,
      "convidados": 0,
      "total": 3,
      "evento": null
    },
    {
      "data": "2025-08-30",
      "patrocinados": 0,
      "organicos": 1,
      "convidados": 0,
      "total": 1,
      "evento": null
    },
    {
      "data": "2025-08-31",
      "patrocinados": 0,
      "organicos": 0,
      "convidados": 0,
      "total": 0,
      "evento": null
    },
    {
      "data": "2025-09-01",
      "patrocinados": 0,
      "organicos": 5,
      "convidados": 0,
      "total": 5,
      "evento": null
    },
    {
      "data": "2025-09-02",
      "patrocinados": 0,
      "organicos": 3,
      "convidados": 0,
      "total": 3,
      "evento": null
    },
    {
      "data": "2025-09-03",
      "patrocinados": 0,
      "organicos": 6,
      "convidados": 0,
      "total": 6,
      "evento": null
    },
    {
      "data": "2025-09-04",
      "patrocinados": 0,
      "organicos": 3,
      "convidados": 0,
      "total": 3,
      "evento": null
    },
    {
      "data": "2025-09-05",
      "patrocinados": 0,
      "organicos": 4,
      "convidados": 0,
      "total": 4,
      "evento": null
    },
    {
      "data": "2025-09-06",
      "patrocinados": 0,
      "organicos": 0,
      "convidados": 0,
      "total": 0,
      "evento": null
    },
    {
      "data": "2025-09-07",
      "patrocinados": 0,
      "organicos": 0,
      "convidados": 0,
      "total": 0,
      "evento": null
    },
    {
      "data": "2025-09-08",
      "patrocinados": 0,
      "organicos": 1,
      "convidados": 0,
      "total": 1,
      "evento": null
    },
    {
      "data": "2025-09-09",
      "patrocinados": 0,
      "organicos": 1,
      "convidados": 0,
      "total": 1,
      "evento": null
    },
    {
      "data": "2025-09-10",
      "patrocinados": 0,
      "organicos": 3,
      "convidados": 0,
      "total": 3,
      "evento": null
    },
    {
      "data": "2025-09-11",
      "patrocinados": 0,
      "organicos": 4,
      "convidados": 0,
      "total": 4,
      "evento": null
    },
    {
      "data": "2025-09-12",
      "patrocinados": 0,
      "organicos": 1,
      "convidados": 0,
      "total": 1,
      "evento": null
    },
    {
      "data": "2025-09-13",
      "patrocinados": 0,
      "organicos": 0,
      "convidados": 0,
      "total": 0,
      "evento": null
    },
    {
      "data": "2025-09-14",
      "patrocinados": 0,
      "organicos": 0,
      "convidados": 0,
      "total": 0,
      "evento": null
    },
    {
      "data": "2025-09-15",
      "patrocinados": 0,
      "organicos": 4,
      "convidados": 0,
      "total": 4,
      "evento": null
    },
    {
      "data": "2025-09-16",
      "patrocinados": 0,
      "organicos": 1,
      "convidados": 0,
      "total": 1,
      "evento": null
    },
    {
      "data": "2025-09-17",
      "patrocinados": 0,
      "organicos": 1,
      "convidados": 0,
      "total": 1,
      "evento": null
    },
    {
      "data": "2025-09-18",
      "patrocinados": 0,
      "organicos": 8,
      "convidados": 0,
      "total": 8,
      "evento": null
    },
    {
      "data": "2025-09-19",
      "patrocinados": 0,
      "organicos": 3,
      "convidados": 0,
      "total": 3,
      "evento": null
    },
    {
      "data": "2025-09-20",
      "patrocinados": 0,
      "organicos": 1,
      "convidados": 0,
      "total": 1,
      "evento": null
    },
    {
      "data": "2025-09-21",
      "patrocinados": 0,
      "organicos": 1,
      "convidados": 0,
      "total": 1,
      "evento": null
    },
    {
      "data": "2025-09-22",
      "patrocinados": 0,
      "organicos": 4,
      "convidados": 0,
      "total": 4,
      "evento": null
    },
    {
      "data": "2025-09-23",
      "patrocinados": 0,
      "organicos": 17,
      "convidados": 0,
      "total": 17,
      "evento": null
    },
    {
      "data": "2025-09-24",
      "patrocinados": 0,
      "organicos": 8,
      "convidados": 0,
      "total": 8,
      "evento": null
    },
    {
      "data": "2025-09-25",
      "patrocinados": 0,
      "organicos": 2,
      "convidados": 0,
      "total": 2,
      "evento": null
    },
    {
      "data": "2025-09-26",
      "patrocinados": 0,
      "organicos": 2,
      "convidados": 0,
      "total": 2,
      "evento": null
    },
    {
      "data": "2025-09-27",
      "patrocinados": 0,
      "organicos": 2,
      "convidados": 0,
      "total": 2,
      "evento": null
    },
    {
      "data": "2025-09-28",
      "patrocinados": 0,
      "organicos": 0,
      "convidados": 0,
      "total": 0,
      "evento": null
    },
    {
      "data": "2025-09-29",
      "patrocinados": 0,
      "organicos": 3,
      "convidados": 0,
      "total": 3,
      "evento": null
    },
    {
      "data": "2025-09-30",
      "patrocinados": 0,
      "organicos": 3,
      "convidados": 0,
      "total": 3,
      "evento": null
    },
    {
      "data": "2025-10-01",
      "patrocinados": 0,
      "organicos": 9,
      "convidados": 0,
      "total": 9,
      "evento": null
    },
    {
      "data": "2025-10-02",
      "patrocinados": 0,
      "organicos": 3,
      "convidados": 0,
      "total": 3,
      "evento": null
    },
    {
      "data": "2025-10-03",
      "patrocinados": 0,
      "organicos": 5,
      "convidados": 0,
      "total": 5,
      "evento": null
    },
    {
      "data": "2025-10-04",
      "patrocinados": 0,
      "organicos": 0,
      "convidados": 0,
      "total": 0,
      "evento": null
    },
    {
      "data": "2025-10-05",
      "patrocinados": 0,
      "organicos": 0,
      "convidados": 0,
      "total": 0,
      "evento": null
    },
    {
      "data": "2025-10-06",
      "patrocinados": 0,
      "organicos": 4,
      "convidados": 0,
      "total": 4,
      "evento": null
    },
    {
      "data": "2025-10-07",
      "patrocinados": 0,
      "organicos": 5,
      "convidados": 0,
      "total": 5,
      "evento": null
    },
    {
      "data": "2025-10-08",
      "patrocinados": 0,
      "organicos": 4,
      "convidados": 0,
      "total": 4,
      "evento": null
    },
    {
      "data": "2025-10-09",
      "patrocinados": 0,
      "organicos": 14,
      "convidados": 0,
      "total": 14,
      "evento": null
    },
    {
      "data": "2025-10-10",
      "patrocinados": 0,
      "organicos": 8,
      "convidados": 0,
      "total": 8,
      "evento": null
    },
    {
      "data": "2025-10-11",
      "patrocinados": 0,
      "organicos": 2,
      "convidados": 0,
      "total": 2,
      "evento": null
    },
    {
      "data": "2025-10-12",
      "patrocinados": 0,
      "organicos": 0,
      "convidados": 0,
      "total": 0,
      "evento": null
    },
    {
      "data": "2025-10-13",
      "patrocinados": 0,
      "organicos": 3,
      "convidados": 0,
      "total": 3,
      "evento": null
    },
    {
      "data": "2025-10-14",
      "patrocinados": 0,
      "organicos": 7,
      "convidados": 0,
      "total": 7,
      "evento": null
    },
    {
      "data": "2025-10-15",
      "patrocinados": 0,
      "organicos": 3,
      "convidados": 0,
      "total": 3,
      "evento": null
    },
    {
      "data": "2025-10-16",
      "patrocinados": 0,
      "organicos": 6,
      "convidados": 0,
      "total": 6,
      "evento": null
    },
    {
      "data": "2025-10-17",
      "patrocinados": 0,
      "organicos": 4,
      "convidados": 0,
      "total": 4,
      "evento": null
    },
    {
      "data": "2025-10-18",
      "patrocinados": 0,
      "organicos": 6,
      "convidados": 0,
      "total": 6,
      "evento": null
    },
    {
      "data": "2025-10-19",
      "patrocinados": 0,
      "organicos": 1,
      "convidados": 0,
      "total": 1,
      "evento": null
    },
    {
      "data": "2025-10-20",
      "patrocinados": 0,
      "organicos": 3,
      "convidados": 0,
      "total": 3,
      "evento": null
    },
    {
      "data": "2025-10-21",
      "patrocinados": 0,
      "organicos": 12,
      "convidados": 0,
      "total": 12,
      "evento": null
    },
    {
      "data": "2025-10-22",
      "patrocinados": 0,
      "organicos": 14,
      "convidados": 0,
      "total": 14,
      "evento": null
    },
    {
      "data": "2025-10-23",
      "patrocinados": 0,
      "organicos": 5,
      "convidados": 0,
      "total": 5,
      "evento": null
    },
    {
      "data": "2025-10-24",
      "patrocinados": 0,
      "organicos": 5,
      "convidados": 0,
      "total": 5,
      "evento": null
    },
    {
      "data": "2025-10-25",
      "patrocinados": 0,
      "organicos": 3,
      "convidados": 0,
      "total": 3,
      "evento": null
    },
    {
      "data": "2025-10-26",
      "patrocinados": 0,
      "organicos": 0,
      "convidados": 0,
      "total": 0,
      "evento": null
    },
    {
      "data": "2025-10-27",
      "patrocinados": 0,
      "organicos": 3,
      "convidados": 0,
      "total": 3,
      "evento": null
    },
    {
      "data": "2025-10-28",
      "patrocinados": 0,
      "organicos": 6,
      "convidados": 0,
      "total": 6,
      "evento": null
    },
    {
      "data": "2025-10-29",
      "patrocinados": 0,
      "organicos": 4,
      "convidados": 0,
      "total": 4,
      "evento": null
    },
    {
      "data": "2025-10-30",
      "patrocinados": 0,
      "organicos": 6,
      "convidados": 0,
      "total": 6,
      "evento": null
    },
    {
      "data": "2025-10-31",
      "patrocinados": 0,
      "organicos": 3,
      "convidados": 0,
      "total": 3,
      "evento": null
    },
    {
      "data": "2025-11-01",
      "patrocinados": 0,
      "organicos": 1,
      "convidados": 0,
      "total": 1,
      "evento": null
    },
    {
      "data": "2025-11-02",
      "patrocinados": 0,
      "organicos": 0,
      "convidados": 0,
      "total": 0,
      "evento": null
    },
    {
      "data": "2025-11-03",
      "patrocinados": 0,
      "organicos": 4,
      "convidados": 0,
      "total": 4,
      "evento": null
    },
    {
      "data": "2025-11-04",
      "patrocinados": 0,
      "organicos": 3,
      "convidados": 0,
      "total": 3,
      "evento": null
    },
    {
      "data": "2025-11-05",
      "patrocinados": 0,
      "organicos": 7,
      "convidados": 0,
      "total": 7,
      "evento": null
    },
    {
      "data": "2025-11-06",
      "patrocinados": 0,
      "organicos": 5,
      "convidados": 0,
      "total": 5,
      "evento": null
    },
    {
      "data": "2025-11-07",
      "patrocinados": 0,
      "organicos": 4,
      "convidados": 0,
      "total": 4,
      "evento": null
    },
    {
      "data": "2025-11-08",
      "patrocinados": 0,
      "organicos": 4,
      "convidados": 0,
      "total": 4,
      "evento": null
    },
    {
      "data": "2025-11-09",
      "patrocinados": 0,
      "organicos": 1,
      "convidados": 0,
      "total": 1,
      "evento": null
    },
    {
      "data": "2025-11-10",
      "patrocinados": 0,
      "organicos": 2,
      "convidados": 0,
      "total": 2,
      "evento": null
    },
    {
      "data": "2025-11-11",
      "patrocinados": 0,
      "organicos": 1,
      "convidados": 0,
      "total": 1,
      "evento": null
    },
    {
      "data": "2025-11-12",
      "patrocinados": 0,
      "organicos": 3,
      "convidados": 0,
      "total": 3,
      "evento": null
    },
    {
      "data": "2025-11-13",
      "patrocinados": 0,
      "organicos": 4,
      "convidados": 0,
      "total": 4,
      "evento": null
    },
    {
      "data": "2025-11-14",
      "patrocinados": 0,
      "organicos": 3,
      "convidados": 0,
      "total": 3,
      "evento": null
    },
    {
      "data": "2025-11-15",
      "patrocinados": 0,
      "organicos": 2,
      "convidados": 0,
      "total": 2,
      "evento": null
    },
    {
      "data": "2025-11-16",
      "patrocinados": 0,
      "organicos": 2,
      "convidados": 0,
      "total": 2,
      "evento": null
    },
    {
      "data": "2025-11-17",
      "patrocinados": 0,
      "organicos": 2,
      "convidados": 0,
      "total": 2,
      "evento": null
    },
    {
      "data": "2025-11-18",
      "patrocinados": 0,
      "organicos": 5,
      "convidados": 0,
      "total": 5,
      "evento": null
    },
    {
      "data": "2025-11-19",
      "patrocinados": 0,
      "organicos": 2,
      "convidados": 0,
      "total": 2,
      "evento": null
    },
    {
      "data": "2025-11-20",
      "patrocinados": 0,
      "organicos": 0,
      "convidados": 0,
      "total": 0,
      "evento": null
    },
    {
      "data": "2025-11-21",
      "patrocinados": 0,
      "organicos": 1,
      "convidados": 0,
      "total": 1,
      "evento": null
    },
    {
      "data": "2025-11-22",
      "patrocinados": 0,
      "organicos": 2,
      "convidados": 0,
      "total": 2,
      "evento": null
    },
    {
      "data": "2025-11-23",
      "patrocinados": 0,
      "organicos": 1,
      "convidados": 0,
      "total": 1,
      "evento": null
    },
    {
      "data": "2025-11-24",
      "patrocinados": 0,
      "organicos": 3,
      "convidados": 0,
      "total": 3,
      "evento": null
    },
    {
      "data": "2025-11-25",
      "patrocinados": 0,
      "organicos": 10,
      "convidados": 0,
      "total": 10,
      "evento": null
    },
    {
      "data": "2025-11-26",
      "patrocinados": 0,
      "organicos": 4,
      "convidados": 0,
      "total": 4,
      "evento": null
    },
    {
      "data": "2025-11-27",
      "patrocinados": 0,
      "organicos": 5,
      "convidados": 0,
      "total": 5,
      "evento": null
    },
    {
      "data": "2025-11-28",
      "patrocinados": 0,
      "organicos": 4,
      "convidados": 0,
      "total": 4,
      "evento": null
    },
    {
      "data": "2025-11-29",
      "patrocinados": 0,
      "organicos": 1,
      "convidados": 0,
      "total": 1,
      "evento": null
    },
    {
      "data": "2025-11-30",
      "patrocinados": 0,
      "organicos": 0,
      "convidados": 0,
      "total": 0,
      "evento": null
    },
    {
      "data": "2025-12-01",
      "patrocinados": 0,
      "organicos": 7,
      "convidados": 0,
      "total": 7,
      "evento": null
    },
    {
      "data": "2025-12-02",
      "patrocinados": 0,
      "organicos": 3,
      "convidados": 0,
      "total": 3,
      "evento": null
    },
    {
      "data": "2025-12-03",
      "patrocinados": 0,
      "organicos": 3,
      "convidados": 0,
      "total": 3,
      "evento": null
    },
    {
      "data": "2025-12-04",
      "patrocinados": 0,
      "organicos": 5,
      "convidados": 0,
      "total": 5,
      "evento": null
    },
    {
      "data": "2025-12-05",
      "patrocinados": 0,
      "organicos": 2,
      "convidados": 0,
      "total": 2,
      "evento": null
    },
    {
      "data": "2025-12-06",
      "patrocinados": 0,
      "organicos": 1,
      "convidados": 0,
      "total": 1,
      "evento": null
    },
    {
      "data": "2025-12-07",
      "patrocinados": 0,
      "organicos": 5,
      "convidados": 0,
      "total": 5,
      "evento": null
    },
    {
      "data": "2025-12-08",
      "patrocinados": 0,
      "organicos": 1,
      "convidados": 0,
      "total": 1,
      "evento": null
    },
    {
      "data": "2025-12-09",
      "patrocinados": 0,
      "organicos": 8,
      "convidados": 0,
      "total": 8,
      "evento": null
    },
    {
      "data": "2025-12-10",
      "patrocinados": 0,
      "organicos": 4,
      "convidados": 0,
      "total": 4,
      "evento": null
    },
    {
      "data": "2025-12-11",
      "patrocinados": 0,
      "organicos": 3,
      "convidados": 0,
      "total": 3,
      "evento": null
    },
    {
      "data": "2025-12-12",
      "patrocinados": 0,
      "organicos": 4,
      "convidados": 0,
      "total": 4,
      "evento": null
    },
    {
      "data": "2025-12-13",
      "patrocinados": 0,
      "organicos": -1,
      "convidados": 0,
      "total": -1,
      "evento": null
    },
    {
      "data": "2025-12-14",
      "patrocinados": 0,
      "organicos": 1,
      "convidados": 0,
      "total": 1,
      "evento": null
    },
    {
      "data": "2025-12-15",
      "patrocinados": 0,
      "organicos": 1,
      "convidados": 0,
      "total": 1,
      "evento": null
    },
    {
      "data": "2025-12-16",
      "patrocinados": 0,
      "organicos": 6,
      "convidados": 0,
      "total": 6,
      "evento": null
    },
    {
      "data": "2025-12-17",
      "patrocinados": 0,
      "organicos": 3,
      "convidados": 0,
      "total": 3,
      "evento": null
    },
    {
      "data": "2025-12-18",
      "patrocinados": 0,
      "organicos": 0,
      "convidados": 0,
      "total": 0,
      "evento": null
    },
    {
      "data": "2025-12-19",
      "patrocinados": 0,
      "organicos": 4,
      "convidados": 0,
      "total": 4,
      "evento": null
    },
    {
      "data": "2025-12-20",
      "patrocinados": 0,
      "organicos": 1,
      "convidados": 0,
      "total": 1,
      "evento": null
    },
    {
      "data": "2025-12-21",
      "patrocinados": 0,
      "organicos": 3,
      "convidados": 0,
      "total": 3,
      "evento": null
    },
    {
      "data": "2025-12-22",
      "patrocinados": 0,
      "organicos": 1,
      "convidados": 0,
      "total": 1,
      "evento": null
    },
    {
      "data": "2025-12-23",
      "patrocinados": 0,
      "organicos": 2,
      "convidados": 0,
      "total": 2,
      "evento": null
    },
    {
      "data": "2025-12-24",
      "patrocinados": 0,
      "organicos": 0,
      "convidados": 0,
      "total": 0,
      "evento": null
    },
    {
      "data": "2025-12-25",
      "patrocinados": 0,
      "organicos": 2,
      "convidados": 0,
      "total": 2,
      "evento": null
    },
    {
      "data": "2025-12-26",
      "patrocinados": 0,
      "organicos": 1,
      "convidados": 0,
      "total": 1,
      "evento": null
    },
    {
      "data": "2025-12-27",
      "patrocinados": 0,
      "organicos": -1,
      "convidados": 0,
      "total": -1,
      "evento": null
    },
    {
      "data": "2025-12-28",
      "patrocinados": 0,
      "organicos": 0,
      "convidados": 0,
      "total": 0,
      "evento": null
    },
    {
      "data": "2025-12-29",
      "patrocinados": 0,
      "organicos": 2,
      "convidados": 0,
      "total": 2,
      "evento": null
    },
    {
      "data": "2025-12-30",
      "patrocinados": 0,
      "organicos": 0,
      "convidados": 0,
      "total": 0,
      "evento": null
    },
    {
      "data": "2025-12-31",
      "patrocinados": 0,
      "organicos": 3,
      "convidados": 0,
      "total": 3,
      "evento": null
    },
    {
      "data": "2026-01-01",
      "patrocinados": 0,
      "organicos": -1,
      "convidados": 0,
      "total": -1,
      "evento": null
    },
    {
      "data": "2026-01-02",
      "patrocinados": 0,
      "organicos": 1,
      "convidados": 0,
      "total": 1,
      "evento": null
    },
    {
      "data": "2026-01-03",
      "patrocinados": 0,
      "organicos": 0,
      "convidados": 0,
      "total": 0,
      "evento": null
    },
    {
      "data": "2026-01-04",
      "patrocinados": 0,
      "organicos": 1,
      "convidados": 0,
      "total": 1,
      "evento": null
    },
    {
      "data": "2026-01-05",
      "patrocinados": 0,
      "organicos": 7,
      "convidados": 0,
      "total": 7,
      "evento": null
    },
    {
      "data": "2026-01-06",
      "patrocinados": 0,
      "organicos": 5,
      "convidados": 0,
      "total": 5,
      "evento": null
    },
    {
      "data": "2026-01-07",
      "patrocinados": 0,
      "organicos": 7,
      "convidados": 0,
      "total": 7,
      "evento": null
    },
    {
      "data": "2026-01-08",
      "patrocinados": 0,
      "organicos": 4,
      "convidados": 0,
      "total": 4,
      "evento": null
    },
    {
      "data": "2026-01-09",
      "patrocinados": 0,
      "organicos": 3,
      "convidados": 0,
      "total": 3,
      "evento": null
    },
    {
      "data": "2026-01-10",
      "patrocinados": 0,
      "organicos": 0,
      "convidados": 0,
      "total": 0,
      "evento": null
    },
    {
      "data": "2026-01-11",
      "patrocinados": 0,
      "organicos": 0,
      "convidados": 0,
      "total": 0,
      "evento": null
    },
    {
      "data": "2026-01-12",
      "patrocinados": 0,
      "organicos": 6,
      "convidados": 0,
      "total": 6,
      "evento": null
    },
    {
      "data": "2026-01-13",
      "patrocinados": 0,
      "organicos": 4,
      "convidados": 0,
      "total": 4,
      "evento": null
    },
    {
      "data": "2026-01-14",
      "patrocinados": 0,
      "organicos": 6,
      "convidados": 0,
      "total": 6,
      "evento": null
    },
    {
      "data": "2026-01-15",
      "patrocinados": 0,
      "organicos": 8,
      "convidados": 0,
      "total": 8,
      "evento": null
    },
    {
      "data": "2026-01-16",
      "patrocinados": 0,
      "organicos": 3,
      "convidados": 0,
      "total": 3,
      "evento": null
    },
    {
      "data": "2026-01-17",
      "patrocinados": 0,
      "organicos": 2,
      "convidados": 0,
      "total": 2,
      "evento": null
    },
    {
      "data": "2026-01-18",
      "patrocinados": 0,
      "organicos": 0,
      "convidados": 0,
      "total": 0,
      "evento": null
    },
    {
      "data": "2026-01-19",
      "patrocinados": 0,
      "organicos": 4,
      "convidados": 0,
      "total": 4,
      "evento": null
    },
    {
      "data": "2026-01-20",
      "patrocinados": 0,
      "organicos": 11,
      "convidados": 0,
      "total": 11,
      "evento": null
    },
    {
      "data": "2026-01-21",
      "patrocinados": 0,
      "organicos": 5,
      "convidados": 0,
      "total": 5,
      "evento": null
    },
    {
      "data": "2026-01-22",
      "patrocinados": 0,
      "organicos": 6,
      "convidados": 0,
      "total": 6,
      "evento": null
    },
    {
      "data": "2026-01-23",
      "patrocinados": 0,
      "organicos": 3,
      "convidados": 0,
      "total": 3,
      "evento": null
    },
    {
      "data": "2026-01-24",
      "patrocinados": 0,
      "organicos": 1,
      "convidados": 0,
      "total": 1,
      "evento": null
    },
    {
      "data": "2026-01-25",
      "patrocinados": 0,
      "organicos": 1,
      "convidados": 0,
      "total": 1,
      "evento": null
    },
    {
      "data": "2026-01-26",
      "patrocinados": 0,
      "organicos": 2,
      "convidados": 0,
      "total": 2,
      "evento": null
    },
    {
      "data": "2026-01-27",
      "patrocinados": 0,
      "organicos": 4,
      "convidados": 0,
      "total": 4,
      "evento": null
    },
    {
      "data": "2026-01-28",
      "patrocinados": 0,
      "organicos": 1,
      "convidados": 0,
      "total": 1,
      "evento": null
    },
    {
      "data": "2026-01-29",
      "patrocinados": 0,
      "organicos": 12,
      "convidados": 0,
      "total": 12,
      "evento": null
    },
    {
      "data": "2026-01-30",
      "patrocinados": 0,
      "organicos": 2,
      "convidados": 0,
      "total": 2,
      "evento": null
    },
    {
      "data": "2026-01-31",
      "patrocinados": 0,
      "organicos": 1,
      "convidados": 0,
      "total": 1,
      "evento": null
    },
    {
      "data": "2026-02-01",
      "patrocinados": 0,
      "organicos": 2,
      "convidados": 0,
      "total": 2,
      "evento": null
    },
    {
      "data": "2026-02-02",
      "patrocinados": 0,
      "organicos": 11,
      "convidados": 0,
      "total": 11,
      "evento": null
    },
    {
      "data": "2026-02-03",
      "patrocinados": 0,
      "organicos": 3,
      "convidados": 0,
      "total": 3,
      "evento": null
    },
    {
      "data": "2026-02-04",
      "patrocinados": 0,
      "organicos": 3,
      "convidados": 0,
      "total": 3,
      "evento": null
    },
    {
      "data": "2026-02-05",
      "patrocinados": 0,
      "organicos": 10,
      "convidados": 0,
      "total": 10,
      "evento": null
    },
    {
      "data": "2026-02-06",
      "patrocinados": 0,
      "organicos": 0,
      "convidados": 0,
      "total": 0,
      "evento": null
    },
    {
      "data": "2026-02-07",
      "patrocinados": 0,
      "organicos": 3,
      "convidados": 0,
      "total": 3,
      "evento": null
    },
    {
      "data": "2026-02-08",
      "patrocinados": 0,
      "organicos": 3,
      "convidados": 0,
      "total": 3,
      "evento": null
    },
    {
      "data": "2026-02-09",
      "patrocinados": 0,
      "organicos": 2,
      "convidados": 0,
      "total": 2,
      "evento": null
    },
    {
      "data": "2026-02-10",
      "patrocinados": 0,
      "organicos": 4,
      "convidados": 0,
      "total": 4,
      "evento": null
    },
    {
      "data": "2026-02-11",
      "patrocinados": 0,
      "organicos": 6,
      "convidados": 0,
      "total": 6,
      "evento": null
    },
    {
      "data": "2026-02-12",
      "patrocinados": 0,
      "organicos": 5,
      "convidados": 0,
      "total": 5,
      "evento": null
    },
    {
      "data": "2026-02-13",
      "patrocinados": 0,
      "organicos": 3,
      "convidados": 0,
      "total": 3,
      "evento": null
    },
    {
      "data": "2026-02-14",
      "patrocinados": 0,
      "organicos": 6,
      "convidados": 0,
      "total": 6,
      "evento": null
    },
    {
      "data": "2026-02-15",
      "patrocinados": 0,
      "organicos": 0,
      "convidados": 0,
      "total": 0,
      "evento": null
    },
    {
      "data": "2026-02-16",
      "patrocinados": 0,
      "organicos": 3,
      "convidados": 0,
      "total": 3,
      "evento": null
    },
    {
      "data": "2026-02-17",
      "patrocinados": 0,
      "organicos": 0,
      "convidados": 0,
      "total": 0,
      "evento": null
    },
    {
      "data": "2026-02-18",
      "patrocinados": 0,
      "organicos": 2,
      "convidados": 0,
      "total": 2,
      "evento": null
    },
    {
      "data": "2026-02-19",
      "patrocinados": 0,
      "organicos": 9,
      "convidados": 0,
      "total": 9,
      "evento": null
    },
    {
      "data": "2026-02-20",
      "patrocinados": 0,
      "organicos": 4,
      "convidados": 0,
      "total": 4,
      "evento": null
    },
    {
      "data": "2026-02-21",
      "patrocinados": 0,
      "organicos": 4,
      "convidados": 0,
      "total": 4,
      "evento": null
    },
    {
      "data": "2026-02-22",
      "patrocinados": 0,
      "organicos": 0,
      "convidados": 0,
      "total": 0,
      "evento": null
    },
    {
      "data": "2026-02-23",
      "patrocinados": 0,
      "organicos": 4,
      "convidados": 0,
      "total": 4,
      "evento": null
    },
    {
      "data": "2026-02-24",
      "patrocinados": 0,
      "organicos": 7,
      "convidados": 0,
      "total": 7,
      "evento": null
    },
    {
      "data": "2026-02-25",
      "patrocinados": 0,
      "organicos": 14,
      "convidados": 0,
      "total": 14,
      "evento": null
    },
    {
      "data": "2026-02-26",
      "patrocinados": 0,
      "organicos": 6,
      "convidados": 0,
      "total": 6,
      "evento": null
    },
    {
      "data": "2026-02-27",
      "patrocinados": 0,
      "organicos": 4,
      "convidados": 0,
      "total": 4,
      "evento": null
    },
    {
      "data": "2026-02-28",
      "patrocinados": 0,
      "organicos": 6,
      "convidados": 0,
      "total": 6,
      "evento": null
    },
    {
      "data": "2026-03-01",
      "patrocinados": 0,
      "organicos": 2,
      "convidados": 0,
      "total": 2,
      "evento": null
    },
    {
      "data": "2026-03-02",
      "patrocinados": 0,
      "organicos": 16,
      "convidados": 0,
      "total": 16,
      "evento": null
    },
    {
      "data": "2026-03-03",
      "patrocinados": 0,
      "organicos": 26,
      "convidados": 0,
      "total": 26,
      "evento": "BTP Experience 2026"
    },
    {
      "data": "2026-03-04",
      "patrocinados": 0,
      "organicos": 10,
      "convidados": 0,
      "total": 10,
      "evento": null
    },
    {
      "data": "2026-03-05",
      "patrocinados": 0,
      "organicos": 8,
      "convidados": 0,
      "total": 8,
      "evento": null
    },
    {
      "data": "2026-03-06",
      "patrocinados": 0,
      "organicos": 2,
      "convidados": 0,
      "total": 2,
      "evento": null
    },
    {
      "data": "2026-03-07",
      "patrocinados": 0,
      "organicos": 4,
      "convidados": 0,
      "total": 4,
      "evento": null
    },
    {
      "data": "2026-03-08",
      "patrocinados": 0,
      "organicos": 4,
      "convidados": 0,
      "total": 4,
      "evento": null
    },
    {
      "data": "2026-03-09",
      "patrocinados": 0,
      "organicos": 4,
      "convidados": 0,
      "total": 4,
      "evento": null
    },
    {
      "data": "2026-03-10",
      "patrocinados": 0,
      "organicos": 3,
      "convidados": 0,
      "total": 3,
      "evento": null
    },
    {
      "data": "2026-03-11",
      "patrocinados": 0,
      "organicos": 12,
      "convidados": 0,
      "total": 12,
      "evento": null
    },
    {
      "data": "2026-03-12",
      "patrocinados": 0,
      "organicos": 12,
      "convidados": 0,
      "total": 12,
      "evento": null
    },
    {
      "data": "2026-03-13",
      "patrocinados": 0,
      "organicos": 21,
      "convidados": 0,
      "total": 21,
      "evento": null
    },
    {
      "data": "2026-03-14",
      "patrocinados": 0,
      "organicos": 7,
      "convidados": 0,
      "total": 7,
      "evento": null
    },
    {
      "data": "2026-03-15",
      "patrocinados": 0,
      "organicos": 3,
      "convidados": 0,
      "total": 3,
      "evento": null
    },
    {
      "data": "2026-03-16",
      "patrocinados": 0,
      "organicos": 6,
      "convidados": 0,
      "total": 6,
      "evento": null
    },
    {
      "data": "2026-03-17",
      "patrocinados": 0,
      "organicos": 8,
      "convidados": 0,
      "total": 8,
      "evento": null
    },
    {
      "data": "2026-03-18",
      "patrocinados": 0,
      "organicos": 5,
      "convidados": 0,
      "total": 5,
      "evento": null
    },
    {
      "data": "2026-03-19",
      "patrocinados": 0,
      "organicos": 4,
      "convidados": 0,
      "total": 4,
      "evento": null
    },
    {
      "data": "2026-03-20",
      "patrocinados": 0,
      "organicos": 2,
      "convidados": 0,
      "total": 2,
      "evento": null
    },
    {
      "data": "2026-03-21",
      "patrocinados": 0,
      "organicos": 4,
      "convidados": 0,
      "total": 4,
      "evento": null
    },
    {
      "data": "2026-03-22",
      "patrocinados": 0,
      "organicos": 1,
      "convidados": 0,
      "total": 1,
      "evento": null
    },
    {
      "data": "2026-03-23",
      "patrocinados": 0,
      "organicos": 8,
      "convidados": 0,
      "total": 8,
      "evento": null
    },
    {
      "data": "2026-03-24",
      "patrocinados": 0,
      "organicos": 9,
      "convidados": 0,
      "total": 9,
      "evento": null
    },
    {
      "data": "2026-03-25",
      "patrocinados": 0,
      "organicos": 17,
      "convidados": 0,
      "total": 17,
      "evento": null
    },
    {
      "data": "2026-03-26",
      "patrocinados": 0,
      "organicos": 7,
      "convidados": 0,
      "total": 7,
      "evento": null
    },
    {
      "data": "2026-03-27",
      "patrocinados": 0,
      "organicos": 9,
      "convidados": 0,
      "total": 9,
      "evento": null
    },
    {
      "data": "2026-03-28",
      "patrocinados": 0,
      "organicos": 4,
      "convidados": 0,
      "total": 4,
      "evento": null
    },
    {
      "data": "2026-03-29",
      "patrocinados": 0,
      "organicos": 4,
      "convidados": 0,
      "total": 4,
      "evento": null
    },
    {
      "data": "2026-03-30",
      "patrocinados": 0,
      "organicos": 3,
      "convidados": 0,
      "total": 3,
      "evento": null
    },
    {
      "data": "2026-03-31",
      "patrocinados": 0,
      "organicos": 6,
      "convidados": 0,
      "total": 6,
      "evento": null
    },
    {
      "data": "2026-04-01",
      "patrocinados": 0,
      "organicos": 7,
      "convidados": 0,
      "total": 7,
      "evento": null
    },
    {
      "data": "2026-04-02",
      "patrocinados": 0,
      "organicos": 2,
      "convidados": 0,
      "total": 2,
      "evento": null
    },
    {
      "data": "2026-04-03",
      "patrocinados": 0,
      "organicos": 5,
      "convidados": 0,
      "total": 5,
      "evento": null
    },
    {
      "data": "2026-04-04",
      "patrocinados": 0,
      "organicos": 1,
      "convidados": 0,
      "total": 1,
      "evento": null
    },
    {
      "data": "2026-04-05",
      "patrocinados": 0,
      "organicos": 1,
      "convidados": 0,
      "total": 1,
      "evento": null
    },
    {
      "data": "2026-04-06",
      "patrocinados": 0,
      "organicos": 12,
      "convidados": 0,
      "total": 12,
      "evento": null
    },
    {
      "data": "2026-04-07",
      "patrocinados": 0,
      "organicos": 7,
      "convidados": 0,
      "total": 7,
      "evento": null
    },
    {
      "data": "2026-04-08",
      "patrocinados": 0,
      "organicos": 8,
      "convidados": 0,
      "total": 8,
      "evento": null
    },
    {
      "data": "2026-04-09",
      "patrocinados": 0,
      "organicos": 2,
      "convidados": 0,
      "total": 2,
      "evento": null
    },
    {
      "data": "2026-04-10",
      "patrocinados": 0,
      "organicos": 6,
      "convidados": 0,
      "total": 6,
      "evento": null
    },
    {
      "data": "2026-04-11",
      "patrocinados": 0,
      "organicos": 1,
      "convidados": 0,
      "total": 1,
      "evento": null
    },
    {
      "data": "2026-04-12",
      "patrocinados": 0,
      "organicos": 0,
      "convidados": 0,
      "total": 0,
      "evento": null
    },
    {
      "data": "2026-04-13",
      "patrocinados": 0,
      "organicos": 3,
      "convidados": 0,
      "total": 3,
      "evento": null
    },
    {
      "data": "2026-04-14",
      "patrocinados": 0,
      "organicos": 7,
      "convidados": 0,
      "total": 7,
      "evento": null
    },
    {
      "data": "2026-04-15",
      "patrocinados": 0,
      "organicos": 3,
      "convidados": 0,
      "total": 3,
      "evento": null
    },
    {
      "data": "2026-04-16",
      "patrocinados": 0,
      "organicos": 5,
      "convidados": 0,
      "total": 5,
      "evento": null
    },
    {
      "data": "2026-04-17",
      "patrocinados": 0,
      "organicos": 7,
      "convidados": 0,
      "total": 7,
      "evento": null
    },
    {
      "data": "2026-04-18",
      "patrocinados": 0,
      "organicos": 5,
      "convidados": 0,
      "total": 5,
      "evento": null
    },
    {
      "data": "2026-04-19",
      "patrocinados": 0,
      "organicos": 0,
      "convidados": 0,
      "total": 0,
      "evento": null
    },
    {
      "data": "2026-04-20",
      "patrocinados": 0,
      "organicos": 3,
      "convidados": 0,
      "total": 3,
      "evento": null
    },
    {
      "data": "2026-04-21",
      "patrocinados": 0,
      "organicos": 5,
      "convidados": 0,
      "total": 5,
      "evento": null
    },
    {
      "data": "2026-04-22",
      "patrocinados": 0,
      "organicos": 6,
      "convidados": 0,
      "total": 6,
      "evento": null
    },
    {
      "data": "2026-04-23",
      "patrocinados": 0,
      "organicos": 9,
      "convidados": 0,
      "total": 9,
      "evento": null
    },
    {
      "data": "2026-04-24",
      "patrocinados": 0,
      "organicos": 6,
      "convidados": 0,
      "total": 6,
      "evento": null
    },
    {
      "data": "2026-04-25",
      "patrocinados": 0,
      "organicos": 2,
      "convidados": 0,
      "total": 2,
      "evento": null
    },
    {
      "data": "2026-04-26",
      "patrocinados": 0,
      "organicos": 1,
      "convidados": 0,
      "total": 1,
      "evento": null
    },
    {
      "data": "2026-04-27",
      "patrocinados": 0,
      "organicos": 8,
      "convidados": 0,
      "total": 8,
      "evento": null
    },
    {
      "data": "2026-04-28",
      "patrocinados": 0,
      "organicos": 6,
      "convidados": 0,
      "total": 6,
      "evento": null
    },
    {
      "data": "2026-04-29",
      "patrocinados": 0,
      "organicos": 11,
      "convidados": 0,
      "total": 11,
      "evento": null
    },
    {
      "data": "2026-04-30",
      "patrocinados": 0,
      "organicos": 9,
      "convidados": 0,
      "total": 9,
      "evento": null
    },
    {
      "data": "2026-05-01",
      "patrocinados": 0,
      "organicos": 1,
      "convidados": 0,
      "total": 1,
      "evento": null
    },
    {
      "data": "2026-05-02",
      "patrocinados": 0,
      "organicos": 1,
      "convidados": 0,
      "total": 1,
      "evento": null
    },
    {
      "data": "2026-05-03",
      "patrocinados": 0,
      "organicos": 1,
      "convidados": 0,
      "total": 1,
      "evento": null
    },
    {
      "data": "2026-05-04",
      "patrocinados": 0,
      "organicos": 14,
      "convidados": 0,
      "total": 14,
      "evento": null
    },
    {
      "data": "2026-05-05",
      "patrocinados": 0,
      "organicos": 5,
      "convidados": 0,
      "total": 5,
      "evento": null
    },
    {
      "data": "2026-05-06",
      "patrocinados": 0,
      "organicos": 4,
      "convidados": 0,
      "total": 4,
      "evento": null
    },
    {
      "data": "2026-05-07",
      "patrocinados": 0,
      "organicos": 4,
      "convidados": 0,
      "total": 4,
      "evento": null
    },
    {
      "data": "2026-05-08",
      "patrocinados": 0,
      "organicos": 9,
      "convidados": 0,
      "total": 9,
      "evento": null
    },
    {
      "data": "2026-05-09",
      "patrocinados": 0,
      "organicos": 3,
      "convidados": 0,
      "total": 3,
      "evento": null
    },
    {
      "data": "2026-05-10",
      "patrocinados": 0,
      "organicos": 0,
      "convidados": 0,
      "total": 0,
      "evento": null
    },
    {
      "data": "2026-05-11",
      "patrocinados": 0,
      "organicos": 8,
      "convidados": 0,
      "total": 8,
      "evento": null
    },
    {
      "data": "2026-05-12",
      "patrocinados": 0,
      "organicos": 9,
      "convidados": 0,
      "total": 9,
      "evento": null
    },
    {
      "data": "2026-05-13",
      "patrocinados": 0,
      "organicos": 16,
      "convidados": 0,
      "total": 16,
      "evento": null
    },
    {
      "data": "2026-05-14",
      "patrocinados": 0,
      "organicos": 3,
      "convidados": 0,
      "total": 3,
      "evento": null
    },
    {
      "data": "2026-05-15",
      "patrocinados": 0,
      "organicos": 6,
      "convidados": 0,
      "total": 6,
      "evento": null
    },
    {
      "data": "2026-05-16",
      "patrocinados": 0,
      "organicos": 28,
      "convidados": 0,
      "total": 28,
      "evento": "Inside Track GO 2026"
    },
    {
      "data": "2026-05-17",
      "patrocinados": 0,
      "organicos": 2,
      "convidados": 0,
      "total": 2,
      "evento": null
    },
    {
      "data": "2026-05-18",
      "patrocinados": 0,
      "organicos": 9,
      "convidados": 0,
      "total": 9,
      "evento": null
    },
    {
      "data": "2026-05-19",
      "patrocinados": 0,
      "organicos": 5,
      "convidados": 0,
      "total": 5,
      "evento": null
    },
    {
      "data": "2026-05-20",
      "patrocinados": 0,
      "organicos": 6,
      "convidados": 0,
      "total": 6,
      "evento": null
    },
    {
      "data": "2026-05-21",
      "patrocinados": 0,
      "organicos": 6,
      "convidados": 0,
      "total": 6,
      "evento": null
    },
    {
      "data": "2026-05-22",
      "patrocinados": 0,
      "organicos": 11,
      "convidados": 0,
      "total": 11,
      "evento": null
    },
    {
      "data": "2026-05-23",
      "patrocinados": 0,
      "organicos": 3,
      "convidados": 0,
      "total": 3,
      "evento": null
    }
  ],
  "eventos": [
    {
      "data": "2025-08-20",
      "patrocinados": 0,
      "organicos": 101,
      "convidados": 0,
      "total": 101,
      "evento": "SAP NOW 2025"
    },
    {
      "data": "2025-08-19",
      "patrocinados": 0,
      "organicos": 72,
      "convidados": 0,
      "total": 72,
      "evento": "SAP NOW 2026"
    },
    {
      "data": "2026-05-16",
      "patrocinados": 0,
      "organicos": 28,
      "convidados": 0,
      "total": 28,
      "evento": "Inside Track GO 2026"
    },
    {
      "data": "2026-03-03",
      "patrocinados": 0,
      "organicos": 26,
      "convidados": 0,
      "total": 26,
      "evento": "BTP Experience 2026"
    }
  ],
  "top10_dias_sem_evento": [
    {
      "data": "2026-03-13",
      "patrocinados": 0,
      "organicos": 21,
      "convidados": 0,
      "total": 21,
      "evento": null
    },
    {
      "data": "2025-09-23",
      "patrocinados": 0,
      "organicos": 17,
      "convidados": 0,
      "total": 17,
      "evento": null
    },
    {
      "data": "2026-03-25",
      "patrocinados": 0,
      "organicos": 17,
      "convidados": 0,
      "total": 17,
      "evento": null
    },
    {
      "data": "2026-03-02",
      "patrocinados": 0,
      "organicos": 16,
      "convidados": 0,
      "total": 16,
      "evento": null
    },
    {
      "data": "2026-05-13",
      "patrocinados": 0,
      "organicos": 16,
      "convidados": 0,
      "total": 16,
      "evento": null
    },
    {
      "data": "2025-10-09",
      "patrocinados": 0,
      "organicos": 14,
      "convidados": 0,
      "total": 14,
      "evento": null
    },
    {
      "data": "2025-10-22",
      "patrocinados": 0,
      "organicos": 14,
      "convidados": 0,
      "total": 14,
      "evento": null
    },
    {
      "data": "2026-02-25",
      "patrocinados": 0,
      "organicos": 14,
      "convidados": 0,
      "total": 14,
      "evento": null
    },
    {
      "data": "2026-05-04",
      "patrocinados": 0,
      "organicos": 14,
      "convidados": 0,
      "total": 14,
      "evento": null
    },
    {
      "data": "2025-10-21",
      "patrocinados": 0,
      "organicos": 12,
      "convidados": 0,
      "total": 12,
      "evento": null
    }
  ],
  "demografia": {
    "Localidade": [
      {
        "label": "São Paulo e Região, Brasil",
        "value": 4096
      },
      {
        "label": "Rio de Janeiro e Região, Brasil",
        "value": 382
      },
      {
        "label": "Campinas e Região, Brasil",
        "value": 368
      },
      {
        "label": "Santo André, Brasil",
        "value": 285
      },
      {
        "label": "Belo Horizonte e Região, Brasil",
        "value": 249
      },
      {
        "label": "Curitiba e Região, Brasil",
        "value": 241
      },
      {
        "label": "Porto Alegre e Região, Brasil",
        "value": 176
      },
      {
        "label": "Recife e Região, Brasil",
        "value": 159
      },
      {
        "label": "Sorocaba, Brasil",
        "value": 146
      },
      {
        "label": "Goiânia e Região, Brasil",
        "value": 121
      },
      {
        "label": "São Caetano do Sul, Brasil",
        "value": 116
      },
      {
        "label": "Brasília e Região, Brasil",
        "value": 116
      },
      {
        "label": "Salvador e Região, Brasil",
        "value": 106
      },
      {
        "label": "São José dos Campos, Brasil",
        "value": 99
      },
      {
        "label": "Fortaleza e Região, Brasil",
        "value": 94
      },
      {
        "label": "Ribeirão Preto e Região, Brasil",
        "value": 87
      },
      {
        "label": "Bogotá D.C. e Região, Colômbia",
        "value": 67
      },
      {
        "label": "Vitória e Região, Brasil",
        "value": 61
      },
      {
        "label": "Florianópolis e Região, Brasil",
        "value": 55
      },
      {
        "label": "Lisboa e Região, Portugal",
        "value": 43
      },
      {
        "label": "Joinville, Brasil",
        "value": 40
      },
      {
        "label": "Hyderabad e Região, Índia",
        "value": 38
      },
      {
        "label": "Joanesburgo e Região, África do Sul",
        "value": 36
      },
      {
        "label": "Bengaluru e Região, Índia",
        "value": 34
      },
      {
        "label": "Diadema, Brasil",
        "value": 34
      },
      {
        "label": "Limeira, Brasil",
        "value": 33
      },
      {
        "label": "Manaus e Região, Brasil",
        "value": 32
      },
      {
        "label": "Bauru, Brasil",
        "value": 32
      },
      {
        "label": "Juiz de Fora, Brasil",
        "value": 31
      },
      {
        "label": "Taubaté, Brasil",
        "value": 30
      },
      {
        "label": "Cidade do México e Região, México",
        "value": 29
      },
      {
        "label": "Araraquara, Brasil",
        "value": 27
      },
      {
        "label": "Atlanta e Região",
        "value": 25
      },
      {
        "label": "Londrina e Região, Brasil",
        "value": 24
      },
      {
        "label": "Lima e Região, Peru",
        "value": 23
      },
      {
        "label": "Londres e Região, Reino Unido, Reino Unido",
        "value": 23
      },
      {
        "label": "Jacareí, Brasil",
        "value": 22
      },
      {
        "label": "Dublin e Região, Irlanda",
        "value": 20
      },
      {
        "label": "Piracicaba, Brasil",
        "value": 20
      },
      {
        "label": "Miami-Fort Lauderdale e Região",
        "value": 20
      },
      {
        "label": "Uberlândia, Brasil",
        "value": 19
      },
      {
        "label": "Santiago e Região, Chile",
        "value": 19
      },
      {
        "label": "São José do Rio Preto, Brasil",
        "value": 19
      },
      {
        "label": "Blumenau, Brasil",
        "value": 19
      },
      {
        "label": "Madrid e Região, Espanha",
        "value": 18
      },
      {
        "label": "Volta Redonda, Brasil",
        "value": 18
      },
      {
        "label": "Mogi Guaçu, Brasil",
        "value": 18
      },
      {
        "label": "São Luís e Região, Brasil",
        "value": 17
      },
      {
        "label": "Rio Verde, Brasil",
        "value": 17
      },
      {
        "label": "Cuiabá e Região, Brasil",
        "value": 16
      },
      {
        "label": "João Pessoa e Região, Brasil",
        "value": 16
      },
      {
        "label": "Nova Iorque e Região",
        "value": 16
      },
      {
        "label": "Pindamonhangaba, Brasil",
        "value": 15
      },
      {
        "label": "Buenos Aires e Região, Argentina",
        "value": 15
      },
      {
        "label": "Serra, Brasil",
        "value": 14
      },
      {
        "label": "Barcelona e Região, Espanha",
        "value": 14
      },
      {
        "label": "Caxias do Sul, Brasil",
        "value": 14
      },
      {
        "label": "Porto e Região, Portugal",
        "value": 13
      },
      {
        "label": "Belém e Região, Brasil",
        "value": 13
      },
      {
        "label": "Pretoria e Região, África do Sul",
        "value": 13
      },
      {
        "label": "Belmonte, Brasil",
        "value": 13
      },
      {
        "label": "Maceió, Brasil",
        "value": 13
      },
      {
        "label": "Aracaju, Brasil",
        "value": 13
      },
      {
        "label": "Santana de Parnaíba, Brasil",
        "value": 12
      },
      {
        "label": "Sydney e Região, Austrália",
        "value": 12
      },
      {
        "label": "Montreal e Região, Canadá",
        "value": 12
      },
      {
        "label": "Atibaia, Brasil",
        "value": 11
      },
      {
        "label": "Campo Grande, Brasil",
        "value": 11
      },
      {
        "label": "Itajaí, Brasil",
        "value": 11
      },
      {
        "label": "Natal e Região, Brasil",
        "value": 11
      },
      {
        "label": "Pune/Pimpri-Chinchwad e Região, Índia",
        "value": 11
      },
      {
        "label": "Manchester e Região, Reino Unido, Reino Unido",
        "value": 11
      },
      {
        "label": "Deli e Região, Índia",
        "value": 11
      },
      {
        "label": "Paris e Região, França",
        "value": 11
      },
      {
        "label": "Dallas-Fort Worth e Região",
        "value": 11
      },
      {
        "label": "Chennai e Região, Índia",
        "value": 11
      },
      {
        "label": "Ourinhos, Brasil",
        "value": 11
      },
      {
        "label": "Toronto e Região, Canadá, Canadá",
        "value": 10
      },
      {
        "label": "Macaé, Brasil",
        "value": 10
      },
      {
        "label": "Chicago e Região",
        "value": 10
      },
      {
        "label": "Embu das Artes, Brasil",
        "value": 10
      },
      {
        "label": "Orlando",
        "value": 9
      },
      {
        "label": "Campos dos Goytacazes, Brasil",
        "value": 9
      },
      {
        "label": "Cajamar, Brasil",
        "value": 9
      },
      {
        "label": "Noida, Índia",
        "value": 9
      },
      {
        "label": "Criciúma, Brasil",
        "value": 9
      },
      {
        "label": "Calcutá e Região, Índia",
        "value": 9
      },
      {
        "label": "São Carlos, Brasil",
        "value": 9
      },
      {
        "label": "Cidade do Cabo, África do Sul",
        "value": 9
      },
      {
        "label": "Maringá, Brasil",
        "value": 9
      },
      {
        "label": "Randstad, Países Baixos",
        "value": 9
      },
      {
        "label": "Braga e Região, Portugal",
        "value": 9
      },
      {
        "label": "Rio das Ostras, Brasil",
        "value": 9
      },
      {
        "label": "Cairo, Egito",
        "value": 9
      },
      {
        "label": "Ponta Grossa, Brasil",
        "value": 8
      },
      {
        "label": "Franco da Rocha, Brasil",
        "value": 8
      },
      {
        "label": "Anápolis, Brasil",
        "value": 8
      },
      {
        "label": "Matão, Brasil",
        "value": 8
      },
      {
        "label": "Teresina, Brasil",
        "value": 8
      },
      {
        "label": "Foz do Iguaçu, Brasil",
        "value": 8
      }
    ],
    "Função": [
      {
        "label": "Tecnologia da informação",
        "value": 2107
      },
      {
        "label": "Desenvolvimento de negócios",
        "value": 860
      },
      {
        "label": "Vendas",
        "value": 764
      },
      {
        "label": "Operações",
        "value": 660
      },
      {
        "label": "Recursos humanos",
        "value": 647
      },
      {
        "label": "Engenharia",
        "value": 585
      },
      {
        "label": "Gestão de projetos",
        "value": 430
      },
      {
        "label": "Marketing",
        "value": 388
      },
      {
        "label": "Consultoria",
        "value": 275
      },
      {
        "label": "Administração",
        "value": 236
      },
      {
        "label": "Financeiro",
        "value": 223
      },
      {
        "label": "Suporte",
        "value": 216
      },
      {
        "label": "Educação",
        "value": 160
      },
      {
        "label": "Mídia e comunicação",
        "value": 142
      },
      {
        "label": "Contabilidade",
        "value": 134
      },
      {
        "label": "Arte e design",
        "value": 119
      },
      {
        "label": "Pesquisa",
        "value": 117
      },
      {
        "label": "Empreendedorismo",
        "value": 109
      },
      {
        "label": "Gestão de produtos",
        "value": 89
      },
      {
        "label": "Serviços sociais e comunitários",
        "value": 76
      },
      {
        "label": "Saúde",
        "value": 75
      },
      {
        "label": "Controle de qualidade",
        "value": 67
      },
      {
        "label": "Imóveis",
        "value": 66
      },
      {
        "label": "Área jurídica",
        "value": 49
      },
      {
        "label": "Compras",
        "value": 48
      },
      {
        "label": "Serviços de proteção e militares",
        "value": 23
      }
    ],
    "Nível de experiência": [
      {
        "label": "Sênior",
        "value": 4490
      },
      {
        "label": "Iniciante",
        "value": 2734
      },
      {
        "label": "Gerente",
        "value": 649
      },
      {
        "label": "Diretor",
        "value": 497
      },
      {
        "label": "Dirigente (CEO, COO, CFO, CMO)",
        "value": 160
      },
      {
        "label": "Proprietário",
        "value": 153
      },
      {
        "label": "Vice-Presidente",
        "value": 127
      },
      {
        "label": "Parceiro",
        "value": 108
      },
      {
        "label": "Treinamento",
        "value": 85
      },
      {
        "label": "Não remunerado",
        "value": 12
      }
    ],
    "Setor": [
      {
        "label": "Atividades dos serviços de tecnologia da informação",
        "value": 2943
      },
      {
        "label": "Desenvolvimento de software",
        "value": 787
      },
      {
        "label": "Atividades de consultoria em gestão empresarial",
        "value": 371
      },
      {
        "label": "Tecnologia, Informação e Internet",
        "value": 236
      },
      {
        "label": "Comércio varejista",
        "value": 228
      },
      {
        "label": "Publicidade e propaganda",
        "value": 218
      },
      {
        "label": "Fornecimento e gestão de recursos humanos",
        "value": 217
      },
      {
        "label": "Atividades de serviços financeiros",
        "value": 175
      },
      {
        "label": "Atividades de contabilidade",
        "value": 165
      },
      {
        "label": "Fabricação de veículos automotores, reboques e carrocerias",
        "value": 154
      },
      {
        "label": "Educação superior",
        "value": 144
      },
      {
        "label": "Intermediação não-monetária - outros instrumentos de captação",
        "value": 137
      },
      {
        "label": "Transporte, armazenagem e correio",
        "value": 114
      },
      {
        "label": "Telecomunicações",
        "value": 112
      },
      {
        "label": "Serviços combinados para apoio a edifícios",
        "value": 104
      },
      {
        "label": "Serviços de alimentação e bebidas",
        "value": 101
      },
      {
        "label": "Agricultura",
        "value": 101
      },
      {
        "label": "Atividades jurídicas",
        "value": 100
      },
      {
        "label": "Fabricação de produtos farmoquímicos e farmacêuticos",
        "value": 97
      },
      {
        "label": "Segurança de redes e computadores",
        "value": 97
      },
      {
        "label": "Hospitais e atividades de atenção à saúde humana",
        "value": 91
      },
      {
        "label": "Seguros e previdência complementar",
        "value": 87
      },
      {
        "label": "Extração de petróleo e gás natural",
        "value": 85
      },
      {
        "label": "Recrutamento e seleção de pessoal",
        "value": 83
      },
      {
        "label": "Marketing",
        "value": 81
      },
      {
        "label": "Construção",
        "value": 76
      },
      {
        "label": "Bancos",
        "value": 72
      },
      {
        "label": "Administração pública, defesa e seguridade social",
        "value": 69
      },
      {
        "label": "Atividades de bem-estar e condicionamento físico",
        "value": 64
      },
      {
        "label": "Comércio varejista de artigos do vestuário e acessórios",
        "value": 63
      },
      {
        "label": "Indústrias de transformação",
        "value": 62
      },
      {
        "label": "Fabricação de máquinas e equipamentos de uso industrial específico",
        "value": 60
      },
      {
        "label": "Planejamento, assessoramento e organização de viagens",
        "value": 59
      },
      {
        "label": "Fabricação de produtos alimentícios e bebidas",
        "value": 57
      },
      {
        "label": "Fabricação de celulose, papel e produtos de papel",
        "value": 56
      },
      {
        "label": "Mineração",
        "value": 55
      },
      {
        "label": "Comércio por atacado",
        "value": 54
      },
      {
        "label": "Fabricação de cosméticos, produtos de perfumaria e de higiene pessoal",
        "value": 54
      },
      {
        "label": "Treinamento em desenvolvimento profissional",
        "value": 52
      },
      {
        "label": "Serviços de informação",
        "value": 51
      },
      {
        "label": "Atividades de apoio à educação",
        "value": 50
      },
      {
        "label": "Serviços advocatícios",
        "value": 50
      },
      {
        "label": "Extração de minerais metálicos",
        "value": 50
      },
      {
        "label": "Atividades de serviços pessoais",
        "value": 50
      },
      {
        "label": "Assessoria em relações públicas e comunicação",
        "value": 49
      },
      {
        "label": "Obras de infra-estrutura",
        "value": 48
      },
      {
        "label": "Serviços de eletricidade, gás, água e esgoto",
        "value": 47
      },
      {
        "label": "Transporte rodoviário de carga",
        "value": 47
      },
      {
        "label": "Serviços de projeto em tecnologia da informação",
        "value": 47
      },
      {
        "label": "Atividades imobiliárias",
        "value": 44
      },
      {
        "label": "Atividades de organizações sem fins lucrativos",
        "value": 43
      },
      {
        "label": "Consultoria de terceirização e offshoring",
        "value": 41
      },
      {
        "label": "Produtos de computação em rede",
        "value": 41
      },
      {
        "label": "Serviços ambientais",
        "value": 39
      },
      {
        "label": "Fabricação de instrumentos e materiais para uso médico e odontológico e de artigos ópticos",
        "value": 37
      },
      {
        "label": "Fabricação de produtos químicos",
        "value": 34
      },
      {
        "label": "Atividades de associações de defesa de direitos sociais",
        "value": 34
      },
      {
        "label": "Educação infantil, ensino fundamental e ensino médio",
        "value": 33
      },
      {
        "label": "Educação",
        "value": 32
      },
      {
        "label": "Serviços de organização, produção e promoção de eventos",
        "value": 31
      },
      {
        "label": "Ensino eletrônico",
        "value": 31
      },
      {
        "label": "Serviços de gestão estratégica",
        "value": 30
      },
      {
        "label": "Fabricação de produtos de material plástico",
        "value": 29
      },
      {
        "label": "Fabricação de máquinas e equipamentos",
        "value": 29
      },
      {
        "label": "Fabricação de peças e acessórios para veículos automotores",
        "value": 29
      },
      {
        "label": "Artes, cultura, esporte e recreação",
        "value": 28
      },
      {
        "label": "Restaurantes e outros serviços de alimentação e bebidas",
        "value": 27
      },
      {
        "label": "Fabricação de máquinas, aparelhos e materiais elétricos",
        "value": 26
      },
      {
        "label": "Fabricação de aeronaves",
        "value": 26
      },
      {
        "label": "Serviços de escritório e apoio administrativo",
        "value": 26
      },
      {
        "label": "Fabricação de produtos têxteis",
        "value": 25
      },
      {
        "label": "Fabricação de máquinas de automação",
        "value": 25
      },
      {
        "label": "Hospitais",
        "value": 23
      },
      {
        "label": "Transporte aéreo",
        "value": 23
      },
      {
        "label": "Serviços de engenharia",
        "value": 23
      },
      {
        "label": "Tecnologia, Informação e Mídia",
        "value": 22
      },
      {
        "label": "Pesquisa e desenvolvimento cientifico",
        "value": 21
      },
      {
        "label": "Atividades de vigilância, segurança e investigação",
        "value": 21
      },
      {
        "label": "Publicação na Internet",
        "value": 20
      },
      {
        "label": "Comércio varejista especializado de equipamentos e suprimentos de informática",
        "value": 19
      },
      {
        "label": "Comércio varejista de material de construção e equipamento de jardinagem",
        "value": 19
      },
      {
        "label": "Pesquisa biotecnológica",
        "value": 18
      },
      {
        "label": "Serviços administrativos e complementares",
        "value": 18
      },
      {
        "label": "Comércio atacadista de materiais de construção em geral",
        "value": 18
      },
      {
        "label": "Geração de energia renovável",
        "value": 18
      },
      {
        "label": "Fabricação de bebidas",
        "value": 18
      },
      {
        "label": "Hotelaria",
        "value": 17
      },
      {
        "label": "Consultórios médicos",
        "value": 17
      },
      {
        "label": "Produtos de software de segurança de dados",
        "value": 17
      },
      {
        "label": "Fabricação de Embalagens e Recipientes",
        "value": 17
      },
      {
        "label": "Fabricação de defensivos agrícolas, adubos e fertilizantes",
        "value": 16
      },
      {
        "label": "Holdings de instituições financeiras e não-financeiras",
        "value": 16
      },
      {
        "label": "Gestão de investimentos em aplicações financeiras",
        "value": 16
      },
      {
        "label": "Desenvolvimento e licenciamento de software customizáveis",
        "value": 15
      },
      {
        "label": "Construção e montagem de aeronaves para fins militares",
        "value": 15
      },
      {
        "label": "Comércio varejista de produtos alimentícios e bebidas",
        "value": 15
      },
      {
        "label": "Serviços de arquitetura e planejamento",
        "value": 15
      },
      {
        "label": "Infraestrutura e análise de dados",
        "value": 15
      },
      {
        "label": "Fabricação de açúcar, chocolate e produtos derivados",
        "value": 14
      },
      {
        "label": "Comércio atacadista de produtos agrícolas não beneficiados",
        "value": 14
      }
    ],
    "Tamanho da empresa": [
      {
        "label": "+ de 10.001",
        "value": 2157
      },
      {
        "label": "1.001-5.000",
        "value": 1429
      },
      {
        "label": "51-200",
        "value": 1243
      },
      {
        "label": "501-1.000",
        "value": 868
      },
      {
        "label": "201-500",
        "value": 809
      },
      {
        "label": "11-50",
        "value": 708
      },
      {
        "label": "5.001-10.000",
        "value": 603
      },
      {
        "label": "2-10",
        "value": 457
      },
      {
        "label": "1",
        "value": 63
      }
    ]
  }
}